MANIFEST.in
README.md
setup.py
test/test.py
tkitW2vec/__init__.py
tkitW2vec/idf.py
tkitW2vec/tw2v.py
tkitW2vec/word2vec_textrank.py
tkitW2vec.egg-info/PKG-INFO
tkitW2vec.egg-info/SOURCES.txt
tkitW2vec.egg-info/dependency_links.txt
tkitW2vec.egg-info/requires.txt
tkitW2vec.egg-info/top_level.txt
tkitW2vec/resources/dict.txt
tkitW2vec/resources/stopwords.txt