Metadata-Version: 2.1
Name: tkitW2vec
Version: 0.0.0.1.4
Summary: tkit包word2vec相关
Home-page: https://terry-toolkit.terrychan.org/zh/master/
Author: Terry Chan
Author-email: napoler2008@gmail.com
License: UNKNOWN
Platform: UNKNOWN
